task_manager/__init__.py
task_manager/admin.py
task_manager/apps.py
task_manager/forms.py
task_manager/models.py
task_manager/tests.py
task_manager/urls.py
task_manager/migrations/0001_initial.py
task_manager/migrations/__init__.py
task_manager/static/task_manager/w3.css
task_manager/templates/task_manager/base.html
task_manager/templates/task_manager/index.html
task_manager/templates/task_manager/login.html
task_manager/templates/task_manager/signup.html
task_manager/templates/task_manager/task_create-edit.html
task_manager/templates/task_manager/task_detail.html
task_manager/templates/task_manager/task_edit.html
task_manager/templates/task_manager/task_search_results.html
task_manager/templates/task_manager/tasks.html
task_manager/templates/task_manager/team_create.html
task_manager/templates/task_manager/team_detail.html
task_manager/views/__init__.py
task_manager/views/auth.py
task_manager/views/index.py
task_manager/views/search.py
task_manager/views/tasks.py
task_manager/views/teams.py
django_task_manager-0.1.dist-info/LICENSE.txt
django_task_manager-0.1.dist-info/METADATA
django_task_manager-0.1.dist-info/WHEEL
django_task_manager-0.1.dist-info/top_level.txt
django_task_manager-0.1.dist-info/RECORD
