Metadata-Version: 2.1
Name: django-task-manager
Version: 0.1
Summary: A multi-user, multi-team task management and assignment system for Django.
Home-page: UNKNOWN
Author: Tushar Patil
Author-email: patiltushar80@yahoo.com
License: BSD License
Platform: UNKNOWN
Classifier: Environment :: Web Environment
Classifier: Framework :: Django
Classifier: License :: OSI Approved :: BSD License
Classifier: Operating System :: OS Independent
Classifier: Programming Language :: Python
Classifier: Programming Language :: Python :: 3
Classifier: Topic :: Software Development :: Bug Tracking
